aioshutil/__init__.py
aioshutil/py.typed
aioshutil-1.5.dist-info/LICENSE.md
aioshutil-1.5.dist-info/METADATA
aioshutil-1.5.dist-info/WHEEL
aioshutil-1.5.dist-info/top_level.txt
aioshutil-1.5.dist-info/RECORD
